datatable/__init__.py
datatable/columns.py
datatable/tables.py
etl/__init__.py
etl/etl_spark.py
etl_spark/__init__.py
etl_spark/from_to.py
etl_spark/datatable/__init__.py
etl_spark/datatable/columns.py
etl_spark/datatable/tables.py
etlspark-1.0.0.1.dist-info/METADATA
etlspark-1.0.0.1.dist-info/WHEEL
etlspark-1.0.0.1.dist-info/top_level.txt
etlspark-1.0.0.1.dist-info/RECORD
